[
  {
    "node": 29239079,
    "note": "start"
  },
  {
    "node": 124524582,
    "note": "travel"
  },
  {
    "node": 29239079,
    "note": "travel"
  },
  {
    "node": 29795235,
    "note": "travel"
  },
  {
    "node": 31777152,
    "note": "travel"
  },
  {
    "node": 29795236,
    "note": "travel"
  },
  {
    "node": 5413741435,
    "note": "travel"
  },
  {
    "node": 29795235,
    "note": "travel"
  },
  {
    "node": 310090260,
    "note": "travel"
  },
  {
    "node": 213649488,
    "note": "travel"
  }
]